sopel_chanlogs/__init__.py
sopel_chanlogs/plugin.py
sopel_chanlogs-0.3.1.dist-info/licenses/COPYING
sopel_chanlogs-0.3.1.dist-info/METADATA
sopel_chanlogs-0.3.1.dist-info/WHEEL
sopel_chanlogs-0.3.1.dist-info/entry_points.txt
sopel_chanlogs-0.3.1.dist-info/top_level.txt
sopel_chanlogs-0.3.1.dist-info/RECORD
