Metadata-Version: 2.4
Name: sopel-chanlogs
Version: 0.3.1
Summary: A channel logging plugin for Sopel IRC bots
Author: David Baumgold, Elsie Powell
Maintainer-email: dgw <dgw@technobabbl.es>
License-Expression: EFL-2.0
Project-URL: Homepage, https://github.com/sopel-irc/sopel-chanlogs
Project-URL: Bug Tracker, https://github.com/sopel-irc/sopel-chanlogs/issues
Keywords: sopel,plugin,bot,irc
Platform: Linux x86, x86-64
Classifier: Development Status :: 4 - Beta
Classifier: Intended Audience :: Developers
Classifier: Intended Audience :: System Administrators
Classifier: Topic :: Communications :: Chat :: Internet Relay Chat
Requires-Python: <4,>=3.8
License-File: COPYING
Requires-Dist: sopel>=8.0
Requires-Dist: pytz
Dynamic: license-file
